vanilla_violin/__init__.py
vanilla_violin/aws/__init__.py
vanilla_violin/aws/aws.py
vanilla_violin/gitlab/__init__.py
vanilla_violin/gitlab/gitlab.py
vanilla_violin-0.1.5.dist-info/LICENSE
vanilla_violin-0.1.5.dist-info/METADATA
vanilla_violin-0.1.5.dist-info/WHEEL
vanilla_violin-0.1.5.dist-info/entry_points.txt
vanilla_violin-0.1.5.dist-info/top_level.txt
vanilla_violin-0.1.5.dist-info/RECORD
