Metadata-Version: 2.1
Name: vanilla-violin
Version: 0.1.5
Summary: Wrappers for AWS and Gitlab APIs
Author-email: Jose Taveira <jose.taveira@mtg.pt>
Classifier: Programming Language :: Python :: 3
Classifier: License :: OSI Approved :: MIT License
Classifier: Operating System :: OS Independent
Requires-Python: >=3.9
License-File: LICENSE
Requires-Dist: Click (>=8.1.3)
Requires-Dist: ddt (>=1.6.0)
Requires-Dist: boto3 (>=1.26.56)
Requires-Dist: requests (>=2.28.1)
Requires-Dist: pytest (>=7.2.0)
Requires-Dist: PyYAML (>=6.0)
